paper_admin/__init__.py
paper_admin/apps.py
paper_admin/conf.py
paper_admin/menu.py
paper_admin/monkey_patch.py
paper_admin/renderer.py
paper_admin/admin/__init__.py
paper_admin/admin/filters.py
paper_admin/admin/forms.py
paper_admin/admin/renderers.py
paper_admin/admin/views.py
paper_admin/admin/widgets.py
paper_admin/locale/ru/LC_MESSAGES/django.mo
paper_admin/locale/ru/LC_MESSAGES/django.po
paper_admin/locale/ru/LC_MESSAGES/djangojs.mo
paper_admin/locale/ru/LC_MESSAGES/djangojs.po
paper_admin/patches/__init__.py
paper_admin/patches/formfield_defaults.py
paper_admin/patches/dal/__init__.py
paper_admin/patches/dal/apps.py
paper_admin/patches/dal/widgets.py
paper_admin/patches/dal/static/autocomplete_light/select2.js
paper_admin/patches/django/__init__.py
paper_admin/patches/django/changelist.py
paper_admin/patches/django/filters.py
paper_admin/patches/django/forms.py
paper_admin/patches/django/helpers.py
paper_admin/patches/django/options.py
paper_admin/patches/django/sites.py
paper_admin/patches/django/prepopulate/__init__.py
paper_admin/patches/django/prepopulate/helpers.py
paper_admin/patches/django/renderer/__init__.py
paper_admin/patches/django/renderer/auth.py
paper_admin/patches/django/renderer/options.py
paper_admin/patches/django/renderer/widgets.py
paper_admin/patches/django/sortable/__init__.py
paper_admin/patches/django/sortable/changelist.py
paper_admin/patches/django/sortable/helpers.py
paper_admin/patches/django/sortable/options.py
paper_admin/patches/django/styles/__init__.py
paper_admin/patches/django/styles/options.py
paper_admin/patches/django/tabs/__init__.py
paper_admin/patches/django/tabs/helpers.py
paper_admin/patches/django/tabs/options.py
paper_admin/patches/django/tabs/utils.py
paper_admin/patches/django/widgets/__init__.py
paper_admin/patches/django/widgets/options.py
paper_admin/patches/django/widgets/widgets.py
paper_admin/patches/django_money/__init__.py
paper_admin/patches/django_money/apps.py
paper_admin-7.7.1.dist-info/LICENSE
paper_admin-7.7.1.dist-info/METADATA
paper_admin-7.7.1.dist-info/WHEEL
paper_admin-7.7.1.dist-info/top_level.txt
paper_admin-7.7.1.dist-info/RECORD
