Metadata-Version: 2.1
Name: paper-admin
Version: 7.7.1
Summary: Custom Django admin interface.
Home-page: https://github.com/dldevinc/paper-admin
Author: Mihail Mishakin
Author-email: x896321475@gmail.com
Maintainer: Mihail Mishakin
Maintainer-email: x896321475@gmail.com
License: BSD license
Platform: OS Independent
Classifier: Intended Audience :: Developers
Classifier: Development Status :: 3 - Alpha
Classifier: License :: OSI Approved :: BSD License
Classifier: Operating System :: OS Independent
Classifier: Framework :: Django :: 3.2
Classifier: Framework :: Django :: 4.0
Classifier: Framework :: Django :: 4.1
Classifier: Framework :: Django :: 4.2
Classifier: Framework :: Django :: 5.0
Classifier: Programming Language :: Python
Classifier: Programming Language :: Python :: 3
Classifier: Programming Language :: Python :: 3 :: Only
Classifier: Programming Language :: Python :: 3.7
Classifier: Programming Language :: Python :: 3.8
Classifier: Programming Language :: Python :: 3.9
Classifier: Programming Language :: Python :: 3.10
Classifier: Programming Language :: Python :: 3.11
Classifier: Programming Language :: Python :: 3.12
Classifier: Topic :: Software Development :: Libraries :: Python Modules
Requires-Python: >=3.7
License-File: LICENSE
Requires-Dist: Django >=3.2
Requires-Dist: Pillow
Requires-Dist: anytree
Requires-Dist: typing-extensions
